bakedpotato/__init__.py
bakedpotato/__main__.py
bakedpotato/potato.py
bakedpotato/assets/potato_baked.png
bakedpotato/assets/potato_raw.png
bakedpotato-1.0.1.dist-info/licenses/LICENSE
bakedpotato-1.0.1.dist-info/METADATA
bakedpotato-1.0.1.dist-info/WHEEL
bakedpotato-1.0.1.dist-info/entry_points.txt
bakedpotato-1.0.1.dist-info/top_level.txt
bakedpotato-1.0.1.dist-info/RECORD
