Metadata-Version: 2.4
Name: bakedpotato
Version: 1.0.1
Summary: A silly pixel-art potato baking simulator
Author-email: Wilf <example@example.com>
Requires-Python: >=3.8
License-File: LICENSE
Requires-Dist: pillow
Dynamic: license-file
